online_store_seminar_6/__init__.py
online_store_seminar_6/__main__.py
online_store_seminar_6/order_management.py
online_store_seminar_6/user_management.py
online_store_homework_6-1.0.0.dist-info/METADATA
online_store_homework_6-1.0.0.dist-info/WHEEL
online_store_homework_6-1.0.0.dist-info/top_level.txt
online_store_homework_6-1.0.0.dist-info/RECORD
