Metadata-Version: 2.1
Name: online-store-homework-6
Version: 1.0.0
Summary: Исполняемый пакет для управления пользователями и заказами в онлайн-магазине
Author-email: brxbxt <89297578555a@gmail.com>
License: MIT
Requires-Python: >=3.8
